{
  "couverture": "/images/uploads/vierge-couverture.jpg",
  "title": "JULIEN",
  "intro": "Nous sommes heureux de vous présenter Julien , nouveau résident à **la Cour des Miracles**, amoureux du _géométrique_, _dotwork_ ou _gravure_ à vos agendas !",
  "shop": "all",
  "galerie": [
    "/images/uploads/mini_julien.png",
    "/images/uploads/img_7367.jpg",
    "/images/uploads/img_7675.jpg",
    "/images/uploads/img_7810.jpg",
    "/images/uploads/img_7851.jpg",
    null
  ],
  "date": "05/01/2019",
  "miniature": "/images/uploads/julien.jpg",
  "description": "Nous sommes heureux de vous présenter Julien , nouveau résident à la cour des miracles, amoureux du géométrique, dotwork ou gravure à vos agendas !"
}